SkillPayload/__init__.py
SkillPayload/load.py
SkillResponse/__init__.py
SkillResponse/common.py
SkillResponse/create.py
SkillResponse/quickreplies.py
kakao_i_python-0.1.dist-info/METADATA
kakao_i_python-0.1.dist-info/WHEEL
kakao_i_python-0.1.dist-info/top_level.txt
kakao_i_python-0.1.dist-info/RECORD
